[
    {
        "business_status": "OPERATIONAL",
        "formatted_address": "1 Farrer Park Station Rd, #01-14/15/16 One Farrer Hotel Connexion, Singapore 217562",
        "geometry": {
            "location": {
                "lat": 1.3124477,
                "lng": 103.8534993
            },
            "viewport": {
                "northeast": {
                    "lat": 1.313605229892722,
                    "lng": 103.8551431798927
                },
                "southwest": {
                    "lat": 1.310905570107278,
                    "lng": 103.8524435201073
                }
            }
        },
        "icon": "https://maps.gstatic.com/mapfiles/place_api/icons/v1/png_71/restaurant-71.png",
        "icon_background_color": "#FF9E67",
        "icon_mask_base_uri": "https://maps.gstatic.com/mapfiles/place_api/icons/v2/restaurant_pinlet",
        "name": "Jia He Chinese Restaurant",
        "opening_hours": {
            "open_now": true
        },
        "photos": [
            {
                "height": 4032,
                "html_attributions": [
                    "<a href=\"https://maps.google.com/maps/contrib/110096814471232819453\">A Google User</a>"
                ],
                "photo_reference": "AUGGfZkHFuGPT1odHQpeIaF7LzVsFqajdt9Ezeo8jS6lah68V_l4mkPNe8irOb4zBfUAPq1IcNmozhdxMCiNJJLqXaS8c_yttoXyHlWGUtxv5ARglbWs8sj_lux-GKDVN7iLyNUK07y4dfWV7Xs4I67NU1OUt43I3BDWA0HzXm25pOxhC_Xz",
                "width": 3024
            }
        ],
        "place_id": "ChIJy1nHKsYZ2jERc5n4bw68rTQ",
        "plus_code": {
            "compound_code": "8V63+X9 Singapore",
            "global_code": "6PH58V63+X9"
        },
        "rating": 4.2,
        "reference": "ChIJy1nHKsYZ2jERc5n4bw68rTQ",
        "types": [
            "meal_delivery",
            "meal_takeaway",
            "restaurant",
            "food",
            "point_of_interest",
            "establishment"
        ],
        "user_ratings_total": 573,
        "Type in AMEX Website": "Asian"
    },
    {
        "business_status": "OPERATIONAL",
        "formatted_address": "88 Amoy St, Singapore 069907",
        "geometry": {
            "location": {
                "lat": 1.2810787,
                "lng": 103.8469579
            },
            "viewport": {
                "northeast": {
                    "lat": 1.282382429892722,
                    "lng": 103.8483912798927
                },
                "southwest": {
                    "lat": 1.279682770107278,
                    "lng": 103.8456916201073
                }
            }
        },
        "icon": "https://maps.gstatic.com/mapfiles/place_api/icons/v1/png_71/restaurant-71.png",
        "icon_background_color": "#FF9E67",
        "icon_mask_base_uri": "https://maps.gstatic.com/mapfiles/place_api/icons/v2/restaurant_pinlet",
        "name": "Lộ Quậy",
        "opening_hours": {
            "open_now": true
        },
        "photos": [
            {
                "height": 2521,
                "html_attributions": [
                    "<a href=\"https://maps.google.com/maps/contrib/101569754843612282374\">A Google User</a>"
                ],
                "photo_reference": "AUGGfZlzfUmbeQeVvpjqeAYZus9LSULAkW_WzJYBWVS_pm19Ce7egPD2muPq6l2URtvRfHVgpdmS0ciw7DVq0umL3_gIGa0hVfulp6F-1ZYftYURLq2iiEgygGwvQE4tbuU_FOkKs0B83q3sQd-KBozQolrbUCRQcPBAWPJx0Sk_4u-LanQ",
                "width": 4701
            }
        ],
        "place_id": "ChIJr2QDkj4Z2jERHQVUMVxXN-4",
        "plus_code": {
            "compound_code": "7RJW+CQ Singapore",
            "global_code": "6PH57RJW+CQ"
        },
        "rating": 4.7,
        "reference": "ChIJr2QDkj4Z2jERHQVUMVxXN-4",
        "types": [
            "restaurant",
            "food",
            "point_of_interest",
            "establishment"
        ],
        "user_ratings_total": 95,
        "Type in AMEX Website": "Asian"
    },
    {
        "business_status": "OPERATIONAL",
        "formatted_address": "65 Chulia St, #33 floor, Singapore 049513",
        "geometry": {
            "location": {
                "lat": 1.285184,
                "lng": 103.8488954
            },
            "viewport": {
                "northeast": {
                    "lat": 1.286443979892722,
                    "lng": 103.8501960798927
                },
                "southwest": {
                    "lat": 1.283744320107278,
                    "lng": 103.8474964201073
                }
            }
        },
        "icon": "https://maps.gstatic.com/mapfiles/place_api/icons/v1/png_71/restaurant-71.png",
        "icon_background_color": "#FF9E67",
        "icon_mask_base_uri": "https://maps.gstatic.com/mapfiles/place_api/icons/v2/restaurant_pinlet",
        "name": "Peach Garden @ OCBC Centre",
        "opening_hours": {
            "open_now": true
        },
        "photos": [
            {
                "height": 3850,
                "html_attributions": [
                    "<a href=\"https://maps.google.com/maps/contrib/110946547174985592811\">A Google User</a>"
                ],
                "photo_reference": "AUGGfZlpWjJVq2a2_Mhir5OjiVQJFtCtVjFI4hEY9onQ0X8h20wPEy4uZGHk7DC_mEsNcedpZkBmB4Ii1Ivp478sZk2BzfXo2nHBXVWmJnixz6sV5X6K90sN0ybMvu2JrO1BiA4e9xLVOnYR9OkCbaLGZFvlPAu62IZ56dbzmIkQGSZRv-Sd",
                "width": 5775
            }
        ],
        "place_id": "ChIJq3cjkwsZ2jER9VpoHY8dtWk",
        "plus_code": {
            "compound_code": "7RPX+3H Singapore",
            "global_code": "6PH57RPX+3H"
        },
        "price_level": 3,
        "rating": 4.1,
        "reference": "ChIJq3cjkwsZ2jER9VpoHY8dtWk",
        "types": [
            "restaurant",
            "point_of_interest",
            "food",
            "establishment"
        ],
        "user_ratings_total": 1679,
        "Type in AMEX Website": "Asian"
    },
    {
        "business_status": "OPERATIONAL",
        "formatted_address": "2 Bayfront Ave, #01 - 86, Singapore 018972",
        "geometry": {
            "location": {
                "lat": 1.2855955,
                "lng": 103.8592972
            },
            "viewport": {
                "northeast": {
                    "lat": 1.286926029892722,
                    "lng": 103.86146665
                },
                "southwest": {
                    "lat": 1.284226370107278,
                    "lng": 103.85857405
                }
            }
        },
        "icon": "https://maps.gstatic.com/mapfiles/place_api/icons/v1/png_71/restaurant-71.png",
        "icon_background_color": "#FF9E67",
        "icon_mask_base_uri": "https://maps.gstatic.com/mapfiles/place_api/icons/v2/restaurant_pinlet",
        "name": "Sen of Japan",
        "opening_hours": {
            "open_now": true
        },
        "photos": [
            {
                "height": 4000,
                "html_attributions": [
                    "<a href=\"https://maps.google.com/maps/contrib/111187084889964478079\">Sen of Japan</a>"
                ],
                "photo_reference": "AUGGfZmARX2UT9Dwl51QMpaIniAam_6vq9ZDHo2kh4FCeieOKajDcvif_kaJnnYczrKWxpRvTT2JxPLsDCHIw5oj7bv8vi0Ml-Vo2kp7V8b5fngYRK4ZSoqIaADvav5Fv8sJd_ZsnYmECPuiEGwQQM6REpI6n5FxCE1bOkNT_ql7Y3BiMn2N",
                "width": 6000
            }
        ],
        "place_id": "ChIJxbfB9QYZ2jERp1oLnDzcGes",
        "plus_code": {
            "compound_code": "7VP5+6P Singapore",
            "global_code": "6PH57VP5+6P"
        },
        "price_level": 3,
        "rating": 4.5,
        "reference": "ChIJxbfB9QYZ2jERp1oLnDzcGes",
        "types": [
            "bar",
            "restaurant",
            "food",
            "point_of_interest",
            "establishment"
        ],
        "user_ratings_total": 1196,
        "Type in AMEX Website": "Asian"
    },
    {
        "business_status": "OPERATIONAL",
        "formatted_address": "80 Raffles Place #60-01, #1 UOB Plaza, Singapore 048624",
        "geometry": {
            "location": {
                "lat": 1.2852812,
                "lng": 103.8503625
            },
            "viewport": {
                "northeast": {
                    "lat": 1.286851179892722,
                    "lng": 103.8515265798927
                },
                "southwest": {
                    "lat": 1.284151520107278,
                    "lng": 103.8488269201073
                }
            }
        },
        "icon": "https://maps.gstatic.com/mapfiles/place_api/icons/v1/png_71/restaurant-71.png",
        "icon_background_color": "#FF9E67",
        "icon_mask_base_uri": "https://maps.gstatic.com/mapfiles/place_api/icons/v2/restaurant_pinlet",
        "name": "Si Chuan Dou Hua Restaurant",
        "opening_hours": {
            "open_now": true
        },
        "photos": [
            {
                "height": 1333,
                "html_attributions": [
                    "<a href=\"https://maps.google.com/maps/contrib/108709888431372341144\">A Google User</a>"
                ],
                "photo_reference": "AUGGfZmPAaXmZccfz2NDP-Opd4QSpUuBGo90wR2xcpkeEpul3kB8KbrCVL8BqrJgrIolsePDLto4zk27CH_LezebEY2g1wpuJSQSQhEBWwGs_ORKCYtEdqbgb0HpH37CdTjGU04_hy8I_wCvu1ldvqci51pqiA3BHMo1BPeDe5vJ2OAkUlDh",
                "width": 2000
            }
        ],
        "place_id": "ChIJAabI4QsZ2jERAe6LcsHDeSI",
        "plus_code": {
            "compound_code": "7VP2+44 Singapore",
            "global_code": "6PH57VP2+44"
        },
        "price_level": 3,
        "rating": 4.1,
        "reference": "ChIJAabI4QsZ2jERAe6LcsHDeSI",
        "types": [
            "cafe",
            "restaurant",
            "food",
            "point_of_interest",
            "establishment"
        ],
        "user_ratings_total": 923,
        "Type in AMEX Website": "Asian"
    },
    {
        "business_status": "OPERATIONAL",
        "formatted_address": "111 Somerset Rd, #01-07, Singapore 238164",
        "geometry": {
            "location": {
                "lat": 1.3004316,
                "lng": 103.8376198
            },
            "viewport": {
                "northeast": {
                    "lat": 1.301816079892722,
                    "lng": 103.8389994798927
                },
                "southwest": {
                    "lat": 1.299116420107278,
                    "lng": 103.8362998201073
                }
            }
        },
        "icon": "https://maps.gstatic.com/mapfiles/place_api/icons/v1/png_71/restaurant-71.png",
        "icon_background_color": "#FF9E67",
        "icon_mask_base_uri": "https://maps.gstatic.com/mapfiles/place_api/icons/v2/restaurant_pinlet",
        "name": "Verandah@Rael's - 111 Somerset",
        "opening_hours": {
            "open_now": false
        },
        "photos": [
            {
                "height": 2463,
                "html_attributions": [
                    "<a href=\"https://maps.google.com/maps/contrib/101635326533602079534\">A Google User</a>"
                ],
                "photo_reference": "AUGGfZkbT9QmjsVgAckyB4spmPjHzmjaXXws2KWj2qsCgke7A4lmrwzwqwM0BaQ4NWPfebc7ObWjjM0rQgk-McTRY9UAmZ2cXHWCT3rix_Vqnl8gH7mHzoaqaGni8HX1TRFvVPwi8a0ROaMPqPUTZ4EKr9IVGa1WNnwmab7vdg9zHySECG87",
                "width": 3411
            }
        ],
        "place_id": "ChIJZbhP0RoZ2jERDyniVrrbUHA",
        "plus_code": {
            "compound_code": "8R2Q+52 Singapore",
            "global_code": "6PH58R2Q+52"
        },
        "rating": 4.5,
        "reference": "ChIJZbhP0RoZ2jERDyniVrrbUHA",
        "types": [
            "restaurant",
            "food",
            "point_of_interest",
            "establishment"
        ],
        "user_ratings_total": 182,
        "Type in AMEX Website": "Asian"
    },
    {
        "business_status": "OPERATIONAL",
        "formatted_address": "317 Outram Rd, Singapore 169075",
        "geometry": {
            "location": {
                "lat": 1.2889324,
                "lng": 103.8346141
            },
            "viewport": {
                "northeast": {
                    "lat": 1.290099279892722,
                    "lng": 103.8356443798927
                },
                "southwest": {
                    "lat": 1.287399620107278,
                    "lng": 103.8329447201073
                }
            }
        },
        "icon": "https://maps.gstatic.com/mapfiles/place_api/icons/v1/png_71/restaurant-71.png",
        "icon_background_color": "#FF9E67",
        "icon_mask_base_uri": "https://maps.gstatic.com/mapfiles/place_api/icons/v2/restaurant_pinlet",
        "name": "Xin Cuisine Chinese Restaurant",
        "opening_hours": {
            "open_now": false
        },
        "photos": [
            {
                "height": 667,
                "html_attributions": [
                    "<a href=\"https://maps.google.com/maps/contrib/118186101370844072900\">Xin Cuisine Chinese Restaurant</a>"
                ],
                "photo_reference": "AUGGfZnlxsNyz-96M5L8VQoWrNukq-nOAdjjz6zIVi438aeFasiBXqmkwMFEBt1q7HnjuVgoDB_2vDJBfxbwnB2jwk3lAPcIONdFbUgkvt-3vNwlWzg2XmSTaN2LFsEt41qw3noDhk2ae0rZrXZg8sYR5umyiaSndFeWHU2ItLOh5DrrbUKj",
                "width": 1000
            }
        ],
        "place_id": "ChIJiVb94HcZ2jERg6qq4TPjM0Y",
        "plus_code": {
            "compound_code": "7RQM+HR Singapore",
            "global_code": "6PH57RQM+HR"
        },
        "rating": 4.5,
        "reference": "ChIJiVb94HcZ2jERg6qq4TPjM0Y",
        "types": [
            "restaurant",
            "point_of_interest",
            "food",
            "establishment"
        ],
        "user_ratings_total": 587,
        "Type in AMEX Website": "Asian"
    },
    {
        "business_status": "OPERATIONAL",
        "formatted_address": "1 St Andrew's Rd, #05-02 National Gallery, Singapore 178957",
        "geometry": {
            "location": {
                "lat": 1.2902783,
                "lng": 103.8517729
            },
            "viewport": {
                "northeast": {
                    "lat": 1.291627429892722,
                    "lng": 103.8531813298927
                },
                "southwest": {
                    "lat": 1.288927770107278,
                    "lng": 103.8504816701073
                }
            }
        },
        "icon": "https://maps.gstatic.com/mapfiles/place_api/icons/v1/png_71/restaurant-71.png",
        "icon_background_color": "#FF9E67",
        "icon_mask_base_uri": "https://maps.gstatic.com/mapfiles/place_api/icons/v2/restaurant_pinlet",
        "name": "Yan Restaurant at National Gallery Singapore 宴中餐馆",
        "opening_hours": {
            "open_now": true
        },
        "photos": [
            {
                "height": 3580,
                "html_attributions": [
                    "<a href=\"https://maps.google.com/maps/contrib/107781091585492943391\">Yàn</a>"
                ],
                "photo_reference": "AUGGfZljuxZlpHdgrLwbzmYnKUiOa9Q2cRa4ZcI7arJplreI4gT7srNlwG8-qOREXXRCfZsRAl4pkibi10mEGNcdH_Yqi2osMDyDR8vsCv9O40svndJVQlmbC2H7tEx-JZAM52-gtendC1HP0S4D6fzb4jQHK781aZSGslQHutK6gNYO8ZNY",
                "width": 4475
            }
        ],
        "place_id": "ChIJLxx8T6cZ2jERXDPzASEmG6k",
        "plus_code": {
            "compound_code": "7VR2+4P Singapore",
            "global_code": "6PH57VR2+4P"
        },
        "price_level": 3,
        "rating": 4.1,
        "reference": "ChIJLxx8T6cZ2jERXDPzASEmG6k",
        "types": [
            "restaurant",
            "food",
            "point_of_interest",
            "establishment"
        ],
        "user_ratings_total": 598,
        "Type in AMEX Website": "Asian"
    },
    {
        "business_status": "OPERATIONAL",
        "formatted_address": "18 Teck Lim Rd, Singapore 088390",
        "geometry": {
            "location": {
                "lat": 1.2804793,
                "lng": 103.8418726
            },
            "viewport": {
                "northeast": {
                    "lat": 1.281807079892722,
                    "lng": 103.8431894798927
                },
                "southwest": {
                    "lat": 1.279107420107277,
                    "lng": 103.8404898201073
                }
            }
        },
        "icon": "https://maps.gstatic.com/mapfiles/place_api/icons/v1/png_71/restaurant-71.png",
        "icon_background_color": "#FF9E67",
        "icon_mask_base_uri": "https://maps.gstatic.com/mapfiles/place_api/icons/v2/restaurant_pinlet",
        "name": "Alegria Singapore",
        "opening_hours": {
            "open_now": true
        },
        "photos": [
            {
                "height": 985,
                "html_attributions": [
                    "<a href=\"https://maps.google.com/maps/contrib/117915405817614814200\">A Google User</a>"
                ],
                "photo_reference": "AUGGfZnyegW3x-3SSUSoXkbViyoOGH4qieRXSOUCJ2sk_fiQYroM8BzLTlM2vofuuSn5q_wocrbrbqs81ChotpQxodaQrvmvyt-pbY29jdjH5aGRCvo3cBE0p_s3PzzxS5ac25STZXxJ-RcHU8M2qJ0mVPr8e2afFLRkT434rStU4CqnnM2X",
                "width": 1414
            }
        ],
        "place_id": "ChIJiezp9N8Z2jERLUeC46XAQNI",
        "plus_code": {
            "compound_code": "7RJR+5P Singapore",
            "global_code": "6PH57RJR+5P"
        },
        "rating": 4.4,
        "reference": "ChIJiezp9N8Z2jERLUeC46XAQNI",
        "types": [
            "restaurant",
            "food",
            "point_of_interest",
            "establishment"
        ],
        "user_ratings_total": 236,
        "Type in AMEX Website": "Contemporary"
    },
    {
        "business_status": "OPERATIONAL",
        "formatted_address": "206 Telok Ayer St, Singapore 068641",
        "geometry": {
            "location": {
                "lat": 1.2800188,
                "lng": 103.847145
            },
            "viewport": {
                "northeast": {
                    "lat": 1.281342779892722,
                    "lng": 103.8485427298927
                },
                "southwest": {
                    "lat": 1.278643120107278,
                    "lng": 103.8458430701073
                }
            }
        },
        "icon": "https://maps.gstatic.com/mapfiles/place_api/icons/v1/png_71/restaurant-71.png",
        "icon_background_color": "#FF9E67",
        "icon_mask_base_uri": "https://maps.gstatic.com/mapfiles/place_api/icons/v2/restaurant_pinlet",
        "name": "Napoleon Wine Bistro",
        "opening_hours": {
            "open_now": true
        },
        "photos": [
            {
                "height": 3072,
                "html_attributions": [
                    "<a href=\"https://maps.google.com/maps/contrib/100101728991252446273\">Joon Hong Kwek</a>"
                ],
                "photo_reference": "AUGGfZmwQ8OPZyg8LYARzvESVzt4drOdpBvCEbp4UFn8_7p93L_wlvuoSW5JS4Hw_l4G5VfubLFzug6eMay_6TOzEnXzlUFlAD60yGp9BtcuNdK5Xp3w4EdOOmoRRiUgW2Gxc8RX2XORr1lWNmEqdJPeFE_34IKii9ILdJoJYiczbg9LxI8e",
                "width": 4080
            }
        ],
        "place_id": "ChIJr-55fA0Z2jERKL4r9-Ep01A",
        "plus_code": {
            "compound_code": "7RJW+2V Singapore",
            "global_code": "6PH57RJW+2V"
        },
        "price_level": 2,
        "rating": 4.2,
        "reference": "ChIJr-55fA0Z2jERKL4r9-Ep01A",
        "types": [
            "bar",
            "liquor_store",
            "restaurant",
            "food",
            "point_of_interest",
            "store",
            "establishment"
        ],
        "user_ratings_total": 625,
        "Type in AMEX Website": "Contemporary"
    },
    {
        "business_status": "OPERATIONAL",
        "formatted_address": "317 Outram Rd, Singapore 169075",
        "geometry": {
            "location": {
                "lat": 1.2888829,
                "lng": 103.834153
            },
            "viewport": {
                "northeast": {
                    "lat": 1.290074529892722,
                    "lng": 103.8354138298927
                },
                "southwest": {
                    "lat": 1.287374870107278,
                    "lng": 103.8327141701073
                }
            }
        },
        "icon": "https://maps.gstatic.com/mapfiles/place_api/icons/v1/png_71/restaurant-71.png",
        "icon_background_color": "#FF9E67",
        "icon_mask_base_uri": "https://maps.gstatic.com/mapfiles/place_api/icons/v2/restaurant_pinlet",
        "name": "Atrium Restaurant",
        "opening_hours": {
            "open_now": false
        },
        "photos": [
            {
                "height": 667,
                "html_attributions": [
                    "<a href=\"https://maps.google.com/maps/contrib/101780120092179761413\">A Google User</a>"
                ],
                "photo_reference": "AUGGfZlZkIJDO7us1s4kfdeHruA5IkLxnys28NEBUfEeho0OTHspRCdTotlGOvm0nwjkOB3qdLGIurFzmkWkIRN91IT8AfH7QGRzMJp_kv3IWujRgrJCVkyr4tKZhFXJt47_blm_imV_Y7wU9u89VeAaoIaOe8qXhRyLNrVT6wRtYsYHfZAJ",
                "width": 1000
            }
        ],
        "place_id": "ChIJiVb94HcZ2jER3ozfH2-Ctro",
        "plus_code": {
            "compound_code": "7RQM+HM Singapore",
            "global_code": "6PH57RQM+HM"
        },
        "rating": 4.4,
        "reference": "ChIJiVb94HcZ2jER3ozfH2-Ctro",
        "types": [
            "restaurant",
            "food",
            "point_of_interest",
            "establishment"
        ],
        "user_ratings_total": 1706,
        "Type in AMEX Website": "International"
    },
    {
        "business_status": "OPERATIONAL",
        "formatted_address": "99 Irrawaddy Rd, Level 22, Singapore 329568",
        "geometry": {
            "location": {
                "lat": 1.3205847,
                "lng": 103.843232
            },
            "viewport": {
                "northeast": {
                    "lat": 1.322092029892722,
                    "lng": 103.8446812298927
                },
                "southwest": {
                    "lat": 1.319392370107278,
                    "lng": 103.8419815701073
                }
            }
        },
        "icon": "https://maps.gstatic.com/mapfiles/place_api/icons/v1/png_71/restaurant-71.png",
        "icon_background_color": "#FF9E67",
        "icon_mask_base_uri": "https://maps.gstatic.com/mapfiles/place_api/icons/v2/restaurant_pinlet",
        "name": "Sky22 @ Courtyard by Marriott",
        "opening_hours": {
            "open_now": true
        },
        "photos": [
            {
                "height": 2490,
                "html_attributions": [
                    "<a href=\"https://maps.google.com/maps/contrib/117367262801540451051\">A Google User</a>"
                ],
                "photo_reference": "AUGGfZlZDQ5LESzpexZfB5T_uUx7Me6rxa0dLN4HQSUy9HBFsJr6RGjXJpistssfm5P0yEXhP-JWeTgM8BjA2HVd-jTz-3nXPH57bNnPPoYmhnqmyp_d5nDVh4NylsBX20IhiDkMldu-BzEzPvg6e6J_3CSmIWPR60FmJySLcc23f8EttUz1",
                "width": 3732
            }
        ],
        "place_id": "ChIJ7z1PPucZ2jERQjFKsB6Nuys",
        "plus_code": {
            "compound_code": "8RCV+67 Singapore",
            "global_code": "6PH58RCV+67"
        },
        "rating": 3.8,
        "reference": "ChIJ7z1PPucZ2jERQjFKsB6Nuys",
        "types": [
            "restaurant",
            "food",
            "point_of_interest",
            "establishment"
        ],
        "user_ratings_total": 289,
        "Type in AMEX Website": "International"
    },
    {
        "business_status": "OPERATIONAL",
        "formatted_address": "1 HarbourFront Walk, #01 - 161/162, Singapore 098585",
        "geometry": {
            "location": {
                "lat": 1.2633811,
                "lng": 103.8215694
            },
            "viewport": {
                "northeast": {
                    "lat": 1.265102079892722,
                    "lng": 103.8225686298927
                },
                "southwest": {
                    "lat": 1.262402420107278,
                    "lng": 103.8198689701073
                }
            }
        },
        "icon": "https://maps.gstatic.com/mapfiles/place_api/icons/v1/png_71/restaurant-71.png",
        "icon_background_color": "#FF9E67",
        "icon_mask_base_uri": "https://maps.gstatic.com/mapfiles/place_api/icons/v2/restaurant_pinlet",
        "name": "Barossa Steak & Grill",
        "opening_hours": {
            "open_now": true
        },
        "photos": [
            {
                "height": 4667,
                "html_attributions": [
                    "<a href=\"https://maps.google.com/maps/contrib/116675207955272717700\">Michael</a>"
                ],
                "photo_reference": "AUGGfZnhGsFmaJ15bXBuzV8bmT9hPP7QOwDrdNB3OnN5knbnIbiBI7JFVye4IOL4q1dZFS1PyIOy5J-K6xdU61bsD3EfBBuK_SFn3Fb5QafXMRoXvEhk_c-nk7nRstRea8tHEbSelfAis2PmdotqkT7Xjr1_YcvHLj_0Dn0z1sV3etJdLk6_",
                "width": 8297
            }
        ],
        "place_id": "ChIJLUCqOP4Z2jERTosPCGAmslk",
        "plus_code": {
            "compound_code": "7R7C+9J Singapore",
            "global_code": "6PH57R7C+9J"
        },
        "rating": 4.6,
        "reference": "ChIJLUCqOP4Z2jERTosPCGAmslk",
        "types": [
            "restaurant",
            "point_of_interest",
            "food",
            "establishment"
        ],
        "user_ratings_total": 2400,
        "Type in AMEX Website": "Western"
    },
    {
        "business_status": "OPERATIONAL",
        "formatted_address": "2 Finlayson Green, Level 2, Singapore 049247",
        "geometry": {
            "location": {
                "lat": 1.2819782,
                "lng": 103.8516656
            },
            "viewport": {
                "northeast": {
                    "lat": 1.283286179892722,
                    "lng": 103.8530786298927
                },
                "southwest": {
                    "lat": 1.280586520107278,
                    "lng": 103.8503789701073
                }
            }
        },
        "icon": "https://maps.gstatic.com/mapfiles/place_api/icons/v1/png_71/restaurant-71.png",
        "icon_background_color": "#FF9E67",
        "icon_mask_base_uri": "https://maps.gstatic.com/mapfiles/place_api/icons/v2/restaurant_pinlet",
        "name": "CALI, Ascott Raffles Place Singapore",
        "opening_hours": {
            "open_now": true
        },
        "photos": [
            {
                "height": 3024,
                "html_attributions": [
                    "<a href=\"https://maps.google.com/maps/contrib/113481456097112069167\">A Google User</a>"
                ],
                "photo_reference": "AUGGfZmfkXjtv2DjvoX_29qJXuVY6XJi8qzPaQ6IJA9uWSSGJvd-7flvzUkFb-iSkLBh7cGeEcWruuvAoV9yxUG3GqiAk3dev4oLiump4BqJrdSQHrs6TFDu4XP7XmR_SCGRBAORuYqPKoPHd1kr2qhYFybUhjPz11QuafYuNDFLmyqSbR4S",
                "width": 4032
            }
        ],
        "place_id": "ChIJk3WecOMZ2jERz12XJdcf3uQ",
        "plus_code": {
            "compound_code": "7VJ2+QM Singapore",
            "global_code": "6PH57VJ2+QM"
        },
        "rating": 4.1,
        "reference": "ChIJk3WecOMZ2jERz12XJdcf3uQ",
        "types": [
            "restaurant",
            "bar",
            "food",
            "point_of_interest",
            "establishment"
        ],
        "user_ratings_total": 463,
        "Type in AMEX Website": "Western"
    },
    {
        "business_status": "OPERATIONAL",
        "formatted_address": "1 Farrer Park Station Rd, One Farrer Hotel, 6th Floor, Singapore 217562",
        "geometry": {
            "location": {
                "lat": 1.3127619,
                "lng": 103.8545562
            },
            "viewport": {
                "northeast": {
                    "lat": 1.313937079892722,
                    "lng": 103.8558509798927
                },
                "southwest": {
                    "lat": 1.311237420107278,
                    "lng": 103.8531513201073
                }
            }
        },
        "icon": "https://maps.gstatic.com/mapfiles/place_api/icons/v1/png_71/restaurant-71.png",
        "icon_background_color": "#FF9E67",
        "icon_mask_base_uri": "https://maps.gstatic.com/mapfiles/place_api/icons/v2/restaurant_pinlet",
        "name": "Escape Restaurant @ One Farrer Hotel",
        "opening_hours": {
            "open_now": true
        },
        "photos": [
            {
                "height": 855,
                "html_attributions": [
                    "<a href=\"https://maps.google.com/maps/contrib/107052614791260659219\">A Google User</a>"
                ],
                "photo_reference": "AUGGfZnPxyduOM8BK3xgsJyR8S1ay0P8YXEaEWthXTzPlr6_qjoZu4SUxKYwNGnl1f5_RyNcdxb-9zrgb6gfvTa7GS3VpbTKJUAJlYt-JPEu1BDPp5KrAVeNoyxzlLNKI5-JUOO-Qk0lzhwHMncLFEi7zj_83PFK99r0d_k60cSiRPA8_M7T",
                "width": 1140
            }
        ],
        "place_id": "ChIJETH01MUZ2jERfBRS39HPGTE",
        "plus_code": {
            "compound_code": "8V73+4R Singapore",
            "global_code": "6PH58V73+4R"
        },
        "price_level": 2,
        "rating": 3.9,
        "reference": "ChIJETH01MUZ2jERfBRS39HPGTE",
        "types": [
            "restaurant",
            "food",
            "point_of_interest",
            "establishment"
        ],
        "user_ratings_total": 419,
        "Type in AMEX Website": "Western"
    },
    {
        "business_status": "OPERATIONAL",
        "formatted_address": "3D River Valley Road, #01-01 Clarke Quay, Singapore 179023",
        "geometry": {
            "location": {
                "lat": 1.2900332,
                "lng": 103.8454485
            },
            "viewport": {
                "northeast": {
                    "lat": 1.291424579892722,
                    "lng": 103.8467626798927
                },
                "southwest": {
                    "lat": 1.288724920107278,
                    "lng": 103.8440630201073
                }
            }
        },
        "icon": "https://maps.gstatic.com/mapfiles/place_api/icons/v1/png_71/restaurant-71.png",
        "icon_background_color": "#FF9E67",
        "icon_mask_base_uri": "https://maps.gstatic.com/mapfiles/place_api/icons/v2/restaurant_pinlet",
        "name": "Harry's Clarke Quay",
        "opening_hours": {
            "open_now": true
        },
        "photos": [
            {
                "height": 2322,
                "html_attributions": [
                    "<a href=\"https://maps.google.com/maps/contrib/111145456892345385117\">Kaptain Kerr</a>"
                ],
                "photo_reference": "AUGGfZmpvdTg6hbAMaY2-qQuyeoUR4Yur9dYUIkHipr0hZEu5iE50y_8qTLG9Yv9UQPqp_qwdFspzODY1TuW-Lwj0jbg7zS1rFmqjifSQO-EQB-bQSvi_trrynycR5PNmoGy1XQM7hu4v3etGm3agDhuLOPnrr6plJUJW0hly47G-dtoCeyy",
                "width": 3941
            }
        ],
        "place_id": "ChIJt1zZZQwZ2jER_dDQnD3ctxU",
        "plus_code": {
            "compound_code": "7RRW+25 Singapore",
            "global_code": "6PH57RRW+25"
        },
        "price_level": 2,
        "rating": 3.9,
        "reference": "ChIJt1zZZQwZ2jER_dDQnD3ctxU",
        "types": [
            "restaurant",
            "bar",
            "point_of_interest",
            "food",
            "establishment"
        ],
        "user_ratings_total": 416,
        "Type in AMEX Website": "Western"
    },
    {
        "business_status": "OPERATIONAL",
        "formatted_address": "26/26B Lor Mambong, Singapore 277685",
        "geometry": {
            "location": {
                "lat": 1.3116821,
                "lng": 103.7948548
            },
            "viewport": {
                "northeast": {
                    "lat": 1.312965479892722,
                    "lng": 103.7961567298927
                },
                "southwest": {
                    "lat": 1.310265820107278,
                    "lng": 103.7934570701073
                }
            }
        },
        "icon": "https://maps.gstatic.com/mapfiles/place_api/icons/v1/png_71/restaurant-71.png",
        "icon_background_color": "#FF9E67",
        "icon_mask_base_uri": "https://maps.gstatic.com/mapfiles/place_api/icons/v2/restaurant_pinlet",
        "name": "La Nonna",
        "opening_hours": {
            "open_now": true
        },
        "photos": [
            {
                "height": 3694,
                "html_attributions": [
                    "<a href=\"https://maps.google.com/maps/contrib/101195889672522028482\">A Google User</a>"
                ],
                "photo_reference": "AUGGfZnGI45R08pprGouw9o7osgJGZ_EVbkZa11mh3uxy6MtiTNGjdWensLpuar7dAgcQmYPCnm10FO2OkyokfLWOU-7eQvOC1ddHeM8pnP3TCSvKVfSX3sTNYoRHdFg7xmTaZYTqqsghci3-EEAcLwCLRkzY3T4Pl-hqUIhK0Nj6mVhzuWr",
                "width": 5534
            }
        ],
        "place_id": "ChIJdc_8l2sa2jERke0T9OeTYq0",
        "plus_code": {
            "compound_code": "8Q6V+MW Singapore",
            "global_code": "6PH58Q6V+MW"
        },
        "price_level": 2,
        "rating": 4.2,
        "reference": "ChIJdc_8l2sa2jERke0T9OeTYq0",
        "types": [
            "bar",
            "restaurant",
            "food",
            "point_of_interest",
            "establishment"
        ],
        "user_ratings_total": 1161,
        "Type in AMEX Website": "Western"
    },
    {
        "business_status": "OPERATIONAL",
        "formatted_address": "333A Orchard Rd, #04 - 01 / 31, Singapore 238897",
        "geometry": {
            "location": {
                "lat": 1.3018632,
                "lng": 103.8369979
            },
            "viewport": {
                "northeast": {
                    "lat": 1.303330929892722,
                    "lng": 103.8383906798927
                },
                "southwest": {
                    "lat": 1.300631270107278,
                    "lng": 103.8356910201073
                }
            }
        },
        "icon": "https://maps.gstatic.com/mapfiles/place_api/icons/v1/png_71/restaurant-71.png",
        "icon_background_color": "#FF9E67",
        "icon_mask_base_uri": "https://maps.gstatic.com/mapfiles/place_api/icons/v2/restaurant_pinlet",
        "name": "Lawry's The Prime Rib Singapore",
        "opening_hours": {
            "open_now": true
        },
        "photos": [
            {
                "height": 5456,
                "html_attributions": [
                    "<a href=\"https://maps.google.com/maps/contrib/116927874216401998957\">Lawry&#39;s The Prime Rib Singapore</a>"
                ],
                "photo_reference": "AUGGfZm4z66uaodPR8IrD9u1fKzlVQ_DwDPkIZdTR5SpiXn9dHiHi0sqqMY3uqo17cH2SG_v6SPm3kaPoZnIWjko3N5Y32CR-WvGht6iTjK8mnf1PopnBnSGf8xJ4CEKIwOA5bR66pU73da9IcXf5D_Ic_gtRSS7HZHQHUR89MEmvFMIKP-n",
                "width": 3632
            }
        ],
        "place_id": "ChIJnwvSIJIZ2jERpSK-8lcGiPk",
        "plus_code": {
            "compound_code": "8R2P+PQ Singapore",
            "global_code": "6PH58R2P+PQ"
        },
        "price_level": 4,
        "rating": 4.4,
        "reference": "ChIJnwvSIJIZ2jERpSK-8lcGiPk",
        "types": [
            "restaurant",
            "point_of_interest",
            "food",
            "establishment"
        ],
        "user_ratings_total": 1454,
        "Type in AMEX Website": "Western"
    },
    {
        "business_status": "OPERATIONAL",
        "formatted_address": "Block 22 Havelock Rd, #01-677, Singapore 160022",
        "geometry": {
            "location": {
                "lat": 1.2886495,
                "lng": 103.8292658
            },
            "viewport": {
                "northeast": {
                    "lat": 1.290033079892722,
                    "lng": 103.8307204798927
                },
                "southwest": {
                    "lat": 1.287333420107278,
                    "lng": 103.8280208201073
                }
            }
        },
        "icon": "https://maps.gstatic.com/mapfiles/place_api/icons/v1/png_71/generic_business-71.png",
        "icon_background_color": "#7B9EB0",
        "icon_mask_base_uri": "https://maps.gstatic.com/mapfiles/place_api/icons/v2/generic_pinlet",
        "name": "Spizza Havelock",
        "opening_hours": {
            "open_now": true
        },
        "photos": [
            {
                "height": 3024,
                "html_attributions": [
                    "<a href=\"https://maps.google.com/maps/contrib/108275532362304111934\">A Google User</a>"
                ],
                "photo_reference": "AUGGfZmpIrQxKlWNnJ9jJ0Qr9RvUNBMUixbedKlmWde7nRcSEMG_sbW-okkU8MxeSko1KMjXdjPSVwW7cIB0FDVkCy-GKvyo7Pnb_Vcm6F7K1t-CMM4WDVaoxc9D3qRIez3FYo0KuItLC4Fvc2iRmII59rjwq639fZddx-rEDzLeK3vQC4KQ",
                "width": 4032
            }
        ],
        "place_id": "ChIJ5RlEhHgZ2jERtb2tpg817OA",
        "plus_code": {
            "compound_code": "7RQH+FP Singapore",
            "global_code": "6PH57RQH+FP"
        },
        "rating": 3.9,
        "reference": "ChIJ5RlEhHgZ2jERtb2tpg817OA",
        "types": [
            "meal_delivery",
            "meal_takeaway",
            "restaurant",
            "food",
            "point_of_interest",
            "establishment"
        ],
        "user_ratings_total": 98,
        "Type in AMEX Website": "Western"
    },
    {
        "business_status": "OPERATIONAL",
        "formatted_address": "10 Coleman St, Level 3, Singapore 179809",
        "geometry": {
            "location": {
                "lat": 1.2924287,
                "lng": 103.8500797
            },
            "viewport": {
                "northeast": {
                    "lat": 1.293710079892722,
                    "lng": 103.8513924298927
                },
                "southwest": {
                    "lat": 1.291010420107278,
                    "lng": 103.8486927701073
                }
            }
        },
        "icon": "https://maps.gstatic.com/mapfiles/place_api/icons/v1/png_71/restaurant-71.png",
        "icon_background_color": "#FF9E67",
        "icon_mask_base_uri": "https://maps.gstatic.com/mapfiles/place_api/icons/v2/restaurant_pinlet",
        "name": "Tablescape Restaurant and Bar",
        "opening_hours": {
            "open_now": true
        },
        "photos": [
            {
                "height": 1591,
                "html_attributions": [
                    "<a href=\"https://maps.google.com/maps/contrib/115352633168279282697\">A Google User</a>"
                ],
                "photo_reference": "AUGGfZnyxTyRS-pyg9Mf2AsDh4fBzRBchXzhktVlTbl6O3MUgVsGoTW71Npb45DJrN-MH1IGPiZM1FyDLMiwD8nS4f2ZuQXfDGqi84kmlCZ17O1OuZc1rN0Y-BC_nrIh8B9vsJCceIAIiymRKujU1hXWZbzF0Bkyt__KRFjkpZIaMPs8FLW5",
                "width": 1061
            }
        ],
        "place_id": "ChIJt0qESaEZ2jER7u_74WZ58yI",
        "plus_code": {
            "compound_code": "7VR2+X2 Singapore",
            "global_code": "6PH57VR2+X2"
        },
        "rating": 4.4,
        "reference": "ChIJt0qESaEZ2jER7u_74WZ58yI",
        "types": [
            "bar",
            "restaurant",
            "food",
            "point_of_interest",
            "establishment"
        ],
        "user_ratings_total": 167,
        "Type in AMEX Website": "Western"
    },
    {
        "business_status": "OPERATIONAL",
        "formatted_address": "33 Hyderabad Road, #02-02 Hort Park, Singapore 119578",
        "geometry": {
            "location": {
                "lat": 1.2789216,
                "lng": 103.8014419
            },
            "viewport": {
                "northeast": {
                    "lat": 1.280143129892722,
                    "lng": 103.8028489798927
                },
                "southwest": {
                    "lat": 1.277443470107278,
                    "lng": 103.8001493201073
                }
            }
        },
        "icon": "https://maps.gstatic.com/mapfiles/place_api/icons/v1/png_71/restaurant-71.png",
        "icon_background_color": "#FF9E67",
        "icon_mask_base_uri": "https://maps.gstatic.com/mapfiles/place_api/icons/v2/restaurant_pinlet",
        "name": "Vineyard",
        "opening_hours": {
            "open_now": true
        },
        "photos": [
            {
                "height": 3632,
                "html_attributions": [
                    "<a href=\"https://maps.google.com/maps/contrib/114869070127449836863\">Vineyard @ Hort Park</a>"
                ],
                "photo_reference": "AUGGfZnlaYGPKiCucd9v5wZKkBnLIQ-cFhYdbha89iob-OWXEDMYd2azFTrqzvoXhrvOeQNrUHj2UKgOu9CMsuLmYP5t82wAWbAcM87cHtSfMls9Z7Zx_yr5uEaDUGRlsYPbCIwJDsTl9nJLXnuCCZ1M67V7z6F0eMSTPkTq78stImzb0teO",
                "width": 5456
            }
        ],
        "place_id": "ChIJw3lZ6ccb2jERiNboEqNCFic",
        "plus_code": {
            "compound_code": "7RH2+HH Singapore",
            "global_code": "6PH57RH2+HH"
        },
        "price_level": 2,
        "rating": 4.5,
        "reference": "ChIJw3lZ6ccb2jERiNboEqNCFic",
        "types": [
            "bar",
            "restaurant",
            "point_of_interest",
            "food",
            "establishment"
        ],
        "user_ratings_total": 1623,
        "Type in AMEX Website": "Western"
    },
    {
        "business_status": "OPERATIONAL",
        "formatted_address": "2 Stamford Rd, Level 3 Swissotel The Stamford, Singapore 178882",
        "geometry": {
            "location": {
                "lat": 1.2931852,
                "lng": 103.8535323
            },
            "viewport": {
                "northeast": {
                    "lat": 1.294743929892722,
                    "lng": 103.8550956298927
                },
                "southwest": {
                    "lat": 1.292044270107278,
                    "lng": 103.8523959701073
                }
            }
        },
        "icon": "https://maps.gstatic.com/mapfiles/place_api/icons/v1/png_71/restaurant-71.png",
        "icon_background_color": "#FF9E67",
        "icon_mask_base_uri": "https://maps.gstatic.com/mapfiles/place_api/icons/v2/restaurant_pinlet",
        "name": "Wooloomooloo Steakhouse Singapore",
        "opening_hours": {
            "open_now": true
        },
        "photos": [
            {
                "height": 3072,
                "html_attributions": [
                    "<a href=\"https://maps.google.com/maps/contrib/112386926962705085336\">112386926962705085336</a>"
                ],
                "photo_reference": "AUGGfZk-l65lvt3_NQAu4RhAwpjtR44Sgq-0VFPqEywqdlZvWLHq_A8pKM0jnK6xtymgKBKxTzQai07qp50omXJGO2VetPumZ08T6bYsvCm-Vn7gTbLx8fPQMOPAfhizN_i2QDx2valnp8HRKj8hs3qXCTeqMQUYvx-eRU9cakg4bjV0w7od",
                "width": 4080
            }
        ],
        "place_id": "ChIJw2RXfaYZ2jERr-j3UWTQdt4",
        "plus_code": {
            "compound_code": "7VV3+7C Singapore",
            "global_code": "6PH57VV3+7C"
        },
        "rating": 4.4,
        "reference": "ChIJw2RXfaYZ2jERr-j3UWTQdt4",
        "types": [
            "bar",
            "restaurant",
            "point_of_interest",
            "food",
            "establishment"
        ],
        "user_ratings_total": 1590,
        "Type in AMEX Website": "Western"
    }
]
